banana_nft/__init__.py
banana_nft/cli.py
banana_nft/client.py
banana_nft/contract_builder.py
banana_nft/exceptions.py
banana_nft/market_intelligence.py
banana_nft/models.py
banana_nft/multi_image_engine.py
banana_nft/rarity_engine.py
banana_nft_sdk-2.0.0.dist-info/LICENSE
banana_nft_sdk-2.0.0.dist-info/METADATA
banana_nft_sdk-2.0.0.dist-info/WHEEL
banana_nft_sdk-2.0.0.dist-info/entry_points.txt
banana_nft_sdk-2.0.0.dist-info/top_level.txt
banana_nft_sdk-2.0.0.dist-info/RECORD
