Metadata-Version: 2.1
Name: banana-nft-sdk
Version: 2.0.0
Summary: 🍌 Revolutionary AI-powered NFT SDK with nano-banana multimodal intelligence
Home-page: https://github.com/banana-nft/sdk
Author: BananaNFT Team
Author-email: hello@banana-nft.ai
Project-URL: Bug Reports, https://github.com/banana-nft/sdk/issues
Project-URL: Source, https://github.com/banana-nft/sdk
Project-URL: Documentation, https://banana-nft.ai/docs
Keywords: nft,ai,art,blockchain,collection,generator,banana,nano-banana,multimodal
Classifier: Development Status :: 5 - Production/Stable
Classifier: Intended Audience :: Developers
Classifier: Topic :: Software Development :: Libraries :: Python Modules
Classifier: Topic :: Multimedia :: Graphics
Classifier: Topic :: Internet :: WWW/HTTP :: Dynamic Content
Classifier: License :: OSI Approved :: MIT License
Classifier: Programming Language :: Python :: 3
Classifier: Programming Language :: Python :: 3.8
Classifier: Programming Language :: Python :: 3.9
Classifier: Programming Language :: Python :: 3.10
Classifier: Programming Language :: Python :: 3.11
Classifier: Programming Language :: Python :: 3.12
Requires-Python: >=3.8
License-File: LICENSE
Requires-Dist: requests >=2.25.0
Requires-Dist: pillow >=8.0.0
Requires-Dist: pydantic >=1.8.0
Requires-Dist: tqdm >=4.60.0
Requires-Dist: python-dotenv >=0.19.0
Provides-Extra: dev
Requires-Dist: pytest >=6.0 ; extra == 'dev'
Requires-Dist: black >=21.0 ; extra == 'dev'
Requires-Dist: flake8 >=3.8 ; extra == 'dev'
Requires-Dist: mypy >=0.800 ; extra == 'dev'
Provides-Extra: docs
Requires-Dist: sphinx >=4.0 ; extra == 'docs'
Requires-Dist: sphinx-rtd-theme >=0.5 ; extra == 'docs'
